wacz_signing/__init__.py
wacz_signing/material.py
wacz_signing/signer.py
wacz_signing-0.4.2.dist-info/COPYING
wacz_signing-0.4.2.dist-info/METADATA
wacz_signing-0.4.2.dist-info/WHEEL
wacz_signing-0.4.2.dist-info/RECORD
