Metadata-Version: 2.1
Name: wacz_signing
Version: 0.4.2
Summary: A library for signing and timestamping file hashes
License: GPL-3.0-or-later
Author: Ben Steinberg
Author-email: bsteinberg@law.harvard.edu
Requires-Python: >=3.11,<4.0
Classifier: License :: OSI Approved :: GNU General Public License v3 or later (GPLv3+)
Classifier: Programming Language :: Python :: 3
Classifier: Programming Language :: Python :: 3.11
Classifier: Programming Language :: Python :: 3.12
Classifier: Programming Language :: Python :: 3.13
Requires-Dist: cryptography (>=44.0.1,<45.0.0)
Requires-Dist: pem (>=21.2.0,<22.0.0)
Requires-Dist: pyasn1 (>=0.4.8,<0.5.0)
Requires-Dist: python-dotenv (>=0.21.0,<0.22.0)
Requires-Dist: rfc3161ng (>=2.1.3,<3.0.0)
